livelog/__init__.py
livelog/__main__.py
livelog/errors.py
livelog/logger.py
livelog/reader.py
livelog-1.0.1.dist-info/LICENSE
livelog-1.0.1.dist-info/WHEEL
livelog-1.0.1.dist-info/METADATA
livelog-1.0.1.dist-info/RECORD
