Metadata-Version: 2.1
Name: livelog
Version: 1.0.1
Summary: File logger and live reader
Home-page: https://github.com/PabloLec/livelog
License: GPL-3.0 License
Keywords: log,logs,logger,reader,utility,console,terminal,livelog,tui,cui
Author: PabloLec
Author-email: pablo.lecolinet@gmail.com
Requires-Python: >=3.7,<4.0
Classifier: Development Status :: 5 - Production/Stable
Classifier: Environment :: Console
Classifier: Intended Audience :: Developers
Classifier: License :: Other/Proprietary License
Classifier: Programming Language :: Python :: 3
Classifier: Programming Language :: Python :: 3.10
Classifier: Programming Language :: Python :: 3.7
Classifier: Programming Language :: Python :: 3.8
Classifier: Programming Language :: Python :: 3.9
Requires-Dist: colorama (==0.4.5)
Requires-Dist: watchdog (==2.1.9)
Project-URL: Documentation, https://github.com/PabloLec/livelog#readme
Project-URL: Repository, https://github.com/PabloLec/livelog
